netbox_cisco_support/__init__.py
netbox_cisco_support/cisco_client.py
netbox_cisco_support/forms.py
netbox_cisco_support/navigation.py
netbox_cisco_support/urls.py
netbox_cisco_support/views.py
netbox_cisco_support/templates/netbox_cisco_support/device_tab.html
netbox_cisco_support/templates/netbox_cisco_support/settings.html
netbox_cisco_support_api-1.0.6.dist-info/licenses/LICENSE
netbox_cisco_support_api-1.0.6.dist-info/METADATA
netbox_cisco_support_api-1.0.6.dist-info/WHEEL
netbox_cisco_support_api-1.0.6.dist-info/top_level.txt
netbox_cisco_support_api-1.0.6.dist-info/RECORD
