Metadata-Version: 2.4
Name: netbox-cisco-support-api
Version: 1.0.6
Summary: NetBox plugin for Cisco Support information including product details, EoX dates, bugs, and security advisories
Author-email: sieteunoseis <jeremy.worden@gmail.com>
License: Apache-2.0
Project-URL: Homepage, https://github.com/sieteunoseis/netbox-cisco-support
Project-URL: Repository, https://github.com/sieteunoseis/netbox-cisco-support.git
Project-URL: Issues, https://github.com/sieteunoseis/netbox-cisco-support/issues
Project-URL: Changelog, https://github.com/sieteunoseis/netbox-cisco-support/blob/main/CHANGELOG.md
Keywords: netbox,cisco,support,eox,psirt,bugs
Classifier: Development Status :: 4 - Beta
Classifier: Framework :: Django
Classifier: Intended Audience :: System Administrators
Classifier: License :: OSI Approved :: Apache Software License
Classifier: Programming Language :: Python :: 3
Classifier: Programming Language :: Python :: 3.10
Classifier: Programming Language :: Python :: 3.11
Classifier: Programming Language :: Python :: 3.12
Classifier: Topic :: System :: Networking
Requires-Python: >=3.10
License-File: LICENSE
Requires-Dist: requests>=2.28.0
Dynamic: license-file
